experts/__init__.py
experts/problems.py
experts/utils.py
experts-0.1.1.dist-info/METADATA
experts-0.1.1.dist-info/WHEEL
experts-0.1.1.dist-info/RECORD
